{
    "version": 2,
    "generated_at": "2026-04-27T19:58:27+00:00",
    "meta": {
        "as_of_date": "2026-04-27",
        "pair": "USDT/USDC",
        "analysis_window_start": "2026-04-15T00:00:00Z",
        "source_window": {
            "start": "2026-04-15T00:00:00Z",
            "end": "2026-04-27T23:59:59Z"
        },
        "active_rung_count": 7,
        "total_trs_in_scope": 446
    },
    "portfolio": {
        "portfolio_value": 50831.173910000005,
        "borrowed": {
            "USDT": 34426.1,
            "USDC": 18856.04
        },
        "borrow_rates_annual": {
            "USDT": 0.038,
            "USDC": 0.038
        },
        "total_fees_to_date": 362.176735
    },
    "active_rungs": [
        {
            "rung": "A",
            "name": "Core",
            "created_at": "2026-04-14T22:50:30Z",
            "range_lower": 0.9979023082300623,
            "range_upper": 1.002904063656376,
            "target_allocation_pct": 54.89,
            "rung_value": 24602.97,
            "fees_to_date": 177.583841,
            "fee_share_pct": 49.03237117094228,
            "efficiency_ratio": 0.8932842261057073,
            "eligible_trs": 446,
            "trades": 329,
            "skipped_count": 6,
            "out_of_range_count": 111,
            "depleted_count": 0,
            "utilization_pct": 73.76681614349776,
            "skipped_pct": 1.345291479820628,
            "out_of_range_pct": 24.887892376681613,
            "depleted_pct": 0,
            "filled_volume_usd": 354976.50064504665,
            "active_days": 12,
            "average_active_capital": 24602.97,
            "capital_days": 295235.64,
            "apr_gross": 0.2195470098562626,
            "predicted_daily_income": 14.798653416666665,
            "predicted_monthly_income": 450.1257080902778,
            "predicted_yearly_income": 5401.508497083333,
            "stability_label": "normal"
        },
        {
            "rung": "B",
            "name": "Buffer",
            "created_at": "2026-04-14T22:53:48Z",
            "range_lower": 0.997403506726374,
            "range_upper": 1.00340561598864,
            "target_allocation_pct": 23.52,
            "rung_value": 10544.08,
            "fees_to_date": 78.54431199999998,
            "fee_share_pct": 21.686735897047605,
            "efficiency_ratio": 0.9220550976635886,
            "eligible_trs": 446,
            "trades": 382,
            "skipped_count": 6,
            "out_of_range_count": 58,
            "depleted_count": 0,
            "utilization_pct": 85.65022421524664,
            "skipped_pct": 1.345291479820628,
            "out_of_range_pct": 13.004484304932735,
            "depleted_pct": 0,
            "filled_volume_usd": 157011.31297083249,
            "active_days": 12,
            "average_active_capital": 10544.08,
            "capital_days": 126528.96,
            "apr_gross": 0.22657796191480584,
            "predicted_daily_income": 6.54535933333333,
            "predicted_monthly_income": 199.08801305555548,
            "predicted_yearly_income": 2389.0561566666656,
            "stability_label": "normal"
        },
        {
            "rung": "C",
            "name": "Scalp",
            "created_at": "2026-04-14T22:56:54Z",
            "range_lower": 0.9988007796361366,
            "range_upper": 1.0021021013305984,
            "target_allocation_pct": 19.75,
            "rung_value": 8852.006261,
            "fees_to_date": 54.41709300000001,
            "fee_share_pct": 15.025010648461452,
            "efficiency_ratio": 0.7607600328334913,
            "eligible_trs": 446,
            "trades": 255,
            "skipped_count": 15,
            "out_of_range_count": 176,
            "depleted_count": 0,
            "utilization_pct": 57.17488789237668,
            "skipped_pct": 3.3632286995515694,
            "out_of_range_pct": 39.46188340807175,
            "depleted_pct": 0,
            "filled_volume_usd": 108765.79926412448,
            "active_days": 12,
            "average_active_capital": 7868.4208406666685,
            "capital_days": 94421.05008800002,
            "apr_gross": 0.2103581661768057,
            "predicted_daily_income": 4.534757750000001,
            "predicted_monthly_income": 137.93221489583337,
            "predicted_yearly_income": 1655.1865787500003,
            "stability_label": "normal"
        },
        {
            "rung": "D",
            "name": "Catch-all",
            "created_at": "2026-04-15T16:17:30Z",
            "range_lower": 0.996406651572219,
            "range_upper": 1.0054143348356561,
            "target_allocation_pct": 1.84,
            "rung_value": 825.431217,
            "fees_to_date": 5.191580999999999,
            "fee_share_pct": 1.433438566947156,
            "efficiency_ratio": 0.7790426994278022,
            "eligible_trs": 402,
            "trades": 383,
            "skipped_count": 19,
            "out_of_range_count": 0,
            "depleted_count": 0,
            "utilization_pct": 95.27363184079603,
            "skipped_pct": 4.72636815920398,
            "out_of_range_pct": 0,
            "depleted_pct": 0,
            "filled_volume_usd": 10378.439572748202,
            "active_days": 12,
            "average_active_capital": 825.431217,
            "capital_days": 9905.174604,
            "apr_gross": 0.19130678062300613,
            "predicted_daily_income": 0.43263174999999987,
            "predicted_monthly_income": 13.159215729166663,
            "predicted_yearly_income": 157.91058874999996,
            "stability_label": "normal"
        },
        {
            "rung": "S1",
            "name": "Tick",
            "created_at": "2026-04-16T19:58:48Z",
            "range_lower": 1.0006001500200015,
            "range_upper": 1.001000450120021,
            "target_allocation_pct": 33.3,
            "rung_value": 2002.303159,
            "fees_to_date": 14.224312000000001,
            "fee_share_pct": 3.9274505028601583,
            "efficiency_ratio": 0.11794145654234711,
            "eligible_trs": 378,
            "trades": 54,
            "skipped_count": 0,
            "out_of_range_count": 324,
            "depleted_count": 0,
            "utilization_pct": 14.285714285714285,
            "skipped_pct": 0,
            "out_of_range_pct": 85.71428571428571,
            "depleted_pct": 0,
            "filled_volume_usd": 28424.4913037711,
            "active_days": 11,
            "average_active_capital": 2020.7357655454541,
            "capital_days": 22228.093420999994,
            "apr_gross": 0.23357261379399177,
            "predicted_daily_income": 1.293119272727273,
            "predicted_monthly_income": 39.33237787878789,
            "predicted_yearly_income": 471.9885345454546,
            "stability_label": "normal"
        },
        {
            "rung": "S2",
            "name": "Flow",
            "created_at": "2026-04-16T20:02:48Z",
            "range_lower": 1.000400060004,
            "range_upper": 1.0012006602200494,
            "target_allocation_pct": 33.3,
            "rung_value": 2001.551475,
            "fees_to_date": 16.156236,
            "fee_share_pct": 4.460870740358295,
            "efficiency_ratio": 0.13396008229304188,
            "eligible_trs": 378,
            "trades": 85,
            "skipped_count": 3,
            "out_of_range_count": 290,
            "depleted_count": 0,
            "utilization_pct": 22.486772486772484,
            "skipped_pct": 0.7936507936507936,
            "out_of_range_pct": 76.71957671957672,
            "depleted_pct": 0,
            "filled_volume_usd": 32287.4674887147,
            "active_days": 11,
            "average_active_capital": 2019.8335075454545,
            "capital_days": 22218.168583,
            "apr_gross": 0.26541459157493513,
            "predicted_daily_income": 1.4687487272727273,
            "predicted_monthly_income": 44.674440454545454,
            "predicted_yearly_income": 536.0932854545455,
            "stability_label": "normal"
        },
        {
            "rung": "S3",
            "name": "Sweep",
            "created_at": "2026-04-16T20:05:24Z",
            "range_lower": 1.00020001,
            "range_upper": 1.0014009103641,
            "target_allocation_pct": 33.3,
            "rung_value": 2002.831798,
            "fees_to_date": 16.05936,
            "fee_share_pct": 4.4341224733830575,
            "efficiency_ratio": 0.13315683103252426,
            "eligible_trs": 378,
            "trades": 107,
            "skipped_count": 3,
            "out_of_range_count": 268,
            "depleted_count": 0,
            "utilization_pct": 28.306878306878307,
            "skipped_pct": 0.7936507936507936,
            "out_of_range_pct": 70.8994708994709,
            "depleted_pct": 0,
            "filled_volume_usd": 32095.0024244087,
            "active_days": 11,
            "average_active_capital": 1966.1989881818176,
            "capital_days": 21628.188869999994,
            "apr_gross": 0.2710197527510311,
            "predicted_daily_income": 1.459941818181818,
            "predicted_monthly_income": 44.406563636363636,
            "predicted_yearly_income": 532.8787636363636,
            "stability_label": "normal"
        }
    ],
    "recent_daily": [
        {
            "date": "2026-04-20",
            "total_fees": 24.229457999999997,
            "trs": 66
        },
        {
            "date": "2026-04-21",
            "total_fees": 53.555484999999976,
            "trs": 51
        },
        {
            "date": "2026-04-22",
            "total_fees": 32.989554999999996,
            "trs": 22
        },
        {
            "date": "2026-04-23",
            "total_fees": 25.567253,
            "trs": 16
        },
        {
            "date": "2026-04-24",
            "total_fees": 0.095956,
            "trs": 2
        },
        {
            "date": "2026-04-26",
            "total_fees": 28.459167,
            "trs": 17
        },
        {
            "date": "2026-04-27",
            "total_fees": 29.853096999999998,
            "trs": 62
        }
    ],
    "bucket_summary": [
        {
            "price_bucket_low": 1,
            "price_bucket_high": 1.0005,
            "tr_count": 1,
            "total_volume_usd": 1109.2672486046,
            "rung_counts": {
                "A": {
                    "participating": 1,
                    "skipped": 0,
                    "depleted": 0,
                    "out_of_range": 0
                },
                "B": {
                    "participating": 1,
                    "skipped": 0,
                    "depleted": 0,
                    "out_of_range": 0
                },
                "C": {
                    "participating": 1,
                    "skipped": 0,
                    "depleted": 0,
                    "out_of_range": 0
                },
                "D": {
                    "participating": 1,
                    "skipped": 0,
                    "depleted": 0,
                    "out_of_range": 0
                },
                "S1": {
                    "participating": 0,
                    "skipped": 0,
                    "depleted": 0,
                    "out_of_range": 1
                },
                "S2": {
                    "participating": 0,
                    "skipped": 0,
                    "depleted": 0,
                    "out_of_range": 1
                },
                "S3": {
                    "participating": 1,
                    "skipped": 0,
                    "depleted": 0,
                    "out_of_range": 0
                }
            }
        },
        {
            "price_bucket_low": 1.0005,
            "price_bucket_high": 1.001,
            "tr_count": 5,
            "total_volume_usd": 22122.504492414602,
            "rung_counts": {
                "A": {
                    "participating": 5,
                    "skipped": 0,
                    "depleted": 0,
                    "out_of_range": 0
                },
                "B": {
                    "participating": 5,
                    "skipped": 0,
                    "depleted": 0,
                    "out_of_range": 0
                },
                "C": {
                    "participating": 5,
                    "skipped": 0,
                    "depleted": 0,
                    "out_of_range": 0
                },
                "D": {
                    "participating": 5,
                    "skipped": 0,
                    "depleted": 0,
                    "out_of_range": 0
                },
                "S1": {
                    "participating": 5,
                    "skipped": 0,
                    "depleted": 0,
                    "out_of_range": 0
                },
                "S2": {
                    "participating": 5,
                    "skipped": 0,
                    "depleted": 0,
                    "out_of_range": 0
                },
                "S3": {
                    "participating": 5,
                    "skipped": 0,
                    "depleted": 0,
                    "out_of_range": 0
                }
            }
        },
        {
            "price_bucket_low": 1.0010000000000001,
            "price_bucket_high": 1.0015,
            "tr_count": 12,
            "total_volume_usd": 9210.700363440197,
            "rung_counts": {
                "A": {
                    "participating": 12,
                    "skipped": 0,
                    "depleted": 0,
                    "out_of_range": 0
                },
                "B": {
                    "participating": 12,
                    "skipped": 0,
                    "depleted": 0,
                    "out_of_range": 0
                },
                "C": {
                    "participating": 12,
                    "skipped": 0,
                    "depleted": 0,
                    "out_of_range": 0
                },
                "D": {
                    "participating": 10,
                    "skipped": 2,
                    "depleted": 0,
                    "out_of_range": 0
                },
                "S1": {
                    "participating": 4,
                    "skipped": 0,
                    "depleted": 0,
                    "out_of_range": 8
                },
                "S2": {
                    "participating": 6,
                    "skipped": 1,
                    "depleted": 0,
                    "out_of_range": 5
                },
                "S3": {
                    "participating": 11,
                    "skipped": 0,
                    "depleted": 0,
                    "out_of_range": 1
                }
            }
        },
        {
            "price_bucket_low": 1.0015,
            "price_bucket_high": 1.002,
            "tr_count": 14,
            "total_volume_usd": 13226.234007209205,
            "rung_counts": {
                "A": {
                    "participating": 14,
                    "skipped": 0,
                    "depleted": 0,
                    "out_of_range": 0
                },
                "B": {
                    "participating": 14,
                    "skipped": 0,
                    "depleted": 0,
                    "out_of_range": 0
                },
                "C": {
                    "participating": 14,
                    "skipped": 0,
                    "depleted": 0,
                    "out_of_range": 0
                },
                "D": {
                    "participating": 13,
                    "skipped": 1,
                    "depleted": 0,
                    "out_of_range": 0
                },
                "S1": {
                    "participating": 0,
                    "skipped": 0,
                    "depleted": 0,
                    "out_of_range": 14
                },
                "S2": {
                    "participating": 0,
                    "skipped": 0,
                    "depleted": 0,
                    "out_of_range": 14
                },
                "S3": {
                    "participating": 0,
                    "skipped": 0,
                    "depleted": 0,
                    "out_of_range": 14
                }
            }
        },
        {
            "price_bucket_low": 1.002,
            "price_bucket_high": 1.0025,
            "tr_count": 23,
            "total_volume_usd": 8036.9534637699,
            "rung_counts": {
                "A": {
                    "participating": 23,
                    "skipped": 0,
                    "depleted": 0,
                    "out_of_range": 0
                },
                "B": {
                    "participating": 23,
                    "skipped": 0,
                    "depleted": 0,
                    "out_of_range": 0
                },
                "C": {
                    "participating": 4,
                    "skipped": 3,
                    "depleted": 0,
                    "out_of_range": 16
                },
                "D": {
                    "participating": 23,
                    "skipped": 0,
                    "depleted": 0,
                    "out_of_range": 0
                },
                "S1": {
                    "participating": 0,
                    "skipped": 0,
                    "depleted": 0,
                    "out_of_range": 23
                },
                "S2": {
                    "participating": 0,
                    "skipped": 0,
                    "depleted": 0,
                    "out_of_range": 23
                },
                "S3": {
                    "participating": 0,
                    "skipped": 0,
                    "depleted": 0,
                    "out_of_range": 23
                }
            }
        },
        {
            "price_bucket_low": 1.0025,
            "price_bucket_high": 1.003,
            "tr_count": 7,
            "total_volume_usd": 5968.4231045826,
            "rung_counts": {
                "A": {
                    "participating": 7,
                    "skipped": 0,
                    "depleted": 0,
                    "out_of_range": 0
                },
                "B": {
                    "participating": 7,
                    "skipped": 0,
                    "depleted": 0,
                    "out_of_range": 0
                },
                "C": {
                    "participating": 0,
                    "skipped": 0,
                    "depleted": 0,
                    "out_of_range": 7
                },
                "D": {
                    "participating": 7,
                    "skipped": 0,
                    "depleted": 0,
                    "out_of_range": 0
                },
                "S1": {
                    "participating": 0,
                    "skipped": 0,
                    "depleted": 0,
                    "out_of_range": 7
                },
                "S2": {
                    "participating": 0,
                    "skipped": 0,
                    "depleted": 0,
                    "out_of_range": 7
                },
                "S3": {
                    "participating": 0,
                    "skipped": 0,
                    "depleted": 0,
                    "out_of_range": 7
                }
            }
        }
    ],
    "alerts": [],
    "recent_tr_examples": [
        {
            "timestamp": "2026-04-27T05:49:12.000Z",
            "trade_price": 1.0018342504585627,
            "price_source": "widest_matching_rung_fill",
            "volume_usd": 0.5246075865000001,
            "fees_usd": 0.000262,
            "participating_rungs": [
                "A",
                "B",
                "C",
                "D"
            ],
            "skipped_rungs": [],
            "depleted_rungs": [],
            "out_of_range_rungs": [
                "S1",
                "S2",
                "S3"
            ]
        },
        {
            "timestamp": "2026-04-27T06:33:48.000Z",
            "trade_price": 1.001750875437719,
            "price_source": "widest_matching_rung_fill",
            "volume_usd": 0.4925539682,
            "fees_usd": 0.000246,
            "participating_rungs": [
                "A",
                "B",
                "C",
                "D"
            ],
            "skipped_rungs": [],
            "depleted_rungs": [],
            "out_of_range_rungs": [
                "S1",
                "S2",
                "S3"
            ]
        },
        {
            "timestamp": "2026-04-27T06:41:36.000Z",
            "trade_price": 1.001750875437719,
            "price_source": "widest_matching_rung_fill",
            "volume_usd": 0.25626608119999994,
            "fees_usd": 0.000128,
            "participating_rungs": [
                "A",
                "B",
                "C",
                "D"
            ],
            "skipped_rungs": [],
            "depleted_rungs": [],
            "out_of_range_rungs": [
                "S1",
                "S2",
                "S3"
            ]
        },
        {
            "timestamp": "2026-04-27T06:42:36.000Z",
            "trade_price": 1.0019905128805329,
            "price_source": "widest_matching_rung_fill",
            "volume_usd": 3004.7460977944997,
            "fees_usd": 1.5059559999999999,
            "participating_rungs": [
                "A",
                "B",
                "C",
                "D"
            ],
            "skipped_rungs": [],
            "depleted_rungs": [],
            "out_of_range_rungs": [
                "S1",
                "S2",
                "S3"
            ]
        },
        {
            "timestamp": "2026-04-27T06:42:48.001Z",
            "trade_price": 1.0020010005002502,
            "price_source": "widest_matching_rung_fill",
            "volume_usd": 0.24634556170000002,
            "fees_usd": 0.000123,
            "participating_rungs": [
                "A",
                "B",
                "D"
            ],
            "skipped_rungs": [
                "C"
            ],
            "depleted_rungs": [],
            "out_of_range_rungs": [
                "S1",
                "S2",
                "S3"
            ]
        },
        {
            "timestamp": "2026-04-27T07:08:24.001Z",
            "trade_price": 1.0021839137172193,
            "price_source": "widest_matching_rung_fill",
            "volume_usd": 352.90793733199996,
            "fees_usd": 0.17691400000000002,
            "participating_rungs": [
                "A",
                "B",
                "D"
            ],
            "skipped_rungs": [],
            "depleted_rungs": [],
            "out_of_range_rungs": [
                "C",
                "S1",
                "S2",
                "S3"
            ]
        },
        {
            "timestamp": "2026-04-27T07:08:36.000Z",
            "trade_price": 1.0020010005002502,
            "price_source": "widest_matching_rung_fill",
            "volume_usd": 0.17626574470000003,
            "fees_usd": 8.8e-5,
            "participating_rungs": [
                "A",
                "B",
                "D"
            ],
            "skipped_rungs": [
                "C"
            ],
            "depleted_rungs": [],
            "out_of_range_rungs": [
                "S1",
                "S2",
                "S3"
            ]
        },
        {
            "timestamp": "2026-04-27T07:38:18.000Z",
            "trade_price": 1.0022511255627815,
            "price_source": "widest_matching_rung_fill",
            "volume_usd": 0.2503975295,
            "fees_usd": 0.000125,
            "participating_rungs": [
                "A",
                "B",
                "D"
            ],
            "skipped_rungs": [],
            "depleted_rungs": [],
            "out_of_range_rungs": [
                "C",
                "S1",
                "S2",
                "S3"
            ]
        },
        {
            "timestamp": "2026-04-27T07:56:06.000Z",
            "trade_price": 1.0022450499318531,
            "price_source": "widest_matching_rung_fill",
            "volume_usd": 473.8515608793,
            "fees_usd": 0.23756000000000002,
            "participating_rungs": [
                "A",
                "B",
                "D"
            ],
            "skipped_rungs": [],
            "depleted_rungs": [],
            "out_of_range_rungs": [
                "C",
                "S1",
                "S2",
                "S3"
            ]
        },
        {
            "timestamp": "2026-04-27T07:56:18.000Z",
            "trade_price": 1.0022511255627815,
            "price_source": "widest_matching_rung_fill",
            "volume_usd": 0.24639243279999998,
            "fees_usd": 0.00012299999999999998,
            "participating_rungs": [
                "A",
                "B",
                "D"
            ],
            "skipped_rungs": [],
            "depleted_rungs": [],
            "out_of_range_rungs": [
                "C",
                "S1",
                "S2",
                "S3"
            ]
        },
        {
            "timestamp": "2026-04-27T08:51:48.000Z",
            "trade_price": 1.0022511255627815,
            "price_source": "widest_matching_rung_fill",
            "volume_usd": 0.3285595816,
            "fees_usd": 0.000164,
            "participating_rungs": [
                "A",
                "B",
                "D"
            ],
            "skipped_rungs": [],
            "depleted_rungs": [],
            "out_of_range_rungs": [
                "C",
                "S1",
                "S2",
                "S3"
            ]
        },
        {
            "timestamp": "2026-04-27T08:54:42.000Z",
            "trade_price": 1.0023709282651756,
            "price_source": "widest_matching_rung_fill",
            "volume_usd": 1227.4705336586,
            "fees_usd": 0.6154949999999999,
            "participating_rungs": [
                "A",
                "B",
                "D"
            ],
            "skipped_rungs": [],
            "depleted_rungs": [],
            "out_of_range_rungs": [
                "C",
                "S1",
                "S2",
                "S3"
            ]
        },
        {
            "timestamp": "2026-04-27T08:54:54.000Z",
            "trade_price": 1.0025012506253128,
            "price_source": "widest_matching_rung_fill",
            "volume_usd": 0.2524336138,
            "fees_usd": 0.000126,
            "participating_rungs": [
                "A",
                "B",
                "D"
            ],
            "skipped_rungs": [],
            "depleted_rungs": [],
            "out_of_range_rungs": [
                "C",
                "S1",
                "S2",
                "S3"
            ]
        },
        {
            "timestamp": "2026-04-27T08:59:36.000Z",
            "trade_price": 1.0025012506253128,
            "price_source": "widest_matching_rung_fill",
            "volume_usd": 0.2965625554,
            "fees_usd": 0.000148,
            "participating_rungs": [
                "A",
                "B",
                "D"
            ],
            "skipped_rungs": [],
            "depleted_rungs": [],
            "out_of_range_rungs": [
                "C",
                "S1",
                "S2",
                "S3"
            ]
        },
        {
            "timestamp": "2026-04-27T09:03:36.000Z",
            "trade_price": 1.0024321614278335,
            "price_source": "widest_matching_rung_fill",
            "volume_usd": 400.29402004869996,
            "fees_usd": 0.19977099999999998,
            "participating_rungs": [
                "A",
                "B",
                "D"
            ],
            "skipped_rungs": [],
            "depleted_rungs": [],
            "out_of_range_rungs": [
                "C",
                "S1",
                "S2",
                "S3"
            ]
        },
        {
            "timestamp": "2026-04-27T09:08:12.000Z",
            "trade_price": 1.0023874276653306,
            "price_source": "widest_matching_rung_fill",
            "volume_usd": 207.2769280501,
            "fees_usd": 0.103455,
            "participating_rungs": [
                "A",
                "B",
                "D"
            ],
            "skipped_rungs": [],
            "depleted_rungs": [],
            "out_of_range_rungs": [
                "C",
                "S1",
                "S2",
                "S3"
            ]
        },
        {
            "timestamp": "2026-04-27T09:26:48.000Z",
            "trade_price": 1.0023441701126696,
            "price_source": "widest_matching_rung_fill",
            "volume_usd": 374.7312382422,
            "fees_usd": 0.187036,
            "participating_rungs": [
                "A",
                "B",
                "D"
            ],
            "skipped_rungs": [],
            "depleted_rungs": [],
            "out_of_range_rungs": [
                "C",
                "S1",
                "S2",
                "S3"
            ]
        },
        {
            "timestamp": "2026-04-27T09:45:42.000Z",
            "trade_price": 1.0022412541151597,
            "price_source": "widest_matching_rung_fill",
            "volume_usd": 1018.5009192719999,
            "fees_usd": 0.508423,
            "participating_rungs": [
                "A",
                "B",
                "D"
            ],
            "skipped_rungs": [],
            "depleted_rungs": [],
            "out_of_range_rungs": [
                "C",
                "S1",
                "S2",
                "S3"
            ]
        },
        {
            "timestamp": "2026-04-27T09:56:48.000Z",
            "trade_price": 1.0022721951791416,
            "price_source": "widest_matching_rung_fill",
            "volume_usd": 1433.5252329834,
            "fees_usd": 0.718732,
            "participating_rungs": [
                "A",
                "B",
                "D"
            ],
            "skipped_rungs": [],
            "depleted_rungs": [],
            "out_of_range_rungs": [
                "C",
                "S1",
                "S2",
                "S3"
            ]
        },
        {
            "timestamp": "2026-04-27T09:57:00.000Z",
            "trade_price": 1.002376188094047,
            "price_source": "widest_matching_rung_fill",
            "volume_usd": 0.5690385735,
            "fees_usd": 0.00028399999999999996,
            "participating_rungs": [
                "A",
                "B",
                "D"
            ],
            "skipped_rungs": [],
            "depleted_rungs": [],
            "out_of_range_rungs": [
                "C",
                "S1",
                "S2",
                "S3"
            ]
        },
        {
            "timestamp": "2026-04-27T10:01:30.000Z",
            "trade_price": 1.0024012006003,
            "price_source": "widest_matching_rung_fill",
            "volume_usd": 0.7393258392,
            "fees_usd": 0.000369,
            "participating_rungs": [
                "A",
                "B",
                "D"
            ],
            "skipped_rungs": [],
            "depleted_rungs": [],
            "out_of_range_rungs": [
                "C",
                "S1",
                "S2",
                "S3"
            ]
        },
        {
            "timestamp": "2026-04-27T10:32:06.000Z",
            "trade_price": 1.0023528841809577,
            "price_source": "widest_matching_rung_fill",
            "volume_usd": 341.9099617932,
            "fees_usd": 0.170664,
            "participating_rungs": [
                "A",
                "B",
                "D"
            ],
            "skipped_rungs": [],
            "depleted_rungs": [],
            "out_of_range_rungs": [
                "C",
                "S1",
                "S2",
                "S3"
            ]
        },
        {
            "timestamp": "2026-04-27T10:38:42.000Z",
            "trade_price": 1.002515484925812,
            "price_source": "widest_matching_rung_fill",
            "volume_usd": 2535.8235374179,
            "fees_usd": 1.271698,
            "participating_rungs": [
                "A",
                "B",
                "D"
            ],
            "skipped_rungs": [],
            "depleted_rungs": [],
            "out_of_range_rungs": [
                "C",
                "S1",
                "S2",
                "S3"
            ]
        },
        {
            "timestamp": "2026-04-27T10:38:54.000Z",
            "trade_price": 1.0026680006670001,
            "price_source": "widest_matching_rung_fill",
            "volume_usd": 0.3888350202,
            "fees_usd": 0.000194,
            "participating_rungs": [
                "A",
                "B",
                "D"
            ],
            "skipped_rungs": [],
            "depleted_rungs": [],
            "out_of_range_rungs": [
                "C",
                "S1",
                "S2",
                "S3"
            ]
        },
        {
            "timestamp": "2026-04-27T10:41:30.000Z",
            "trade_price": 1.002731876077288,
            "price_source": "widest_matching_rung_fill",
            "volume_usd": 384.9059116488,
            "fees_usd": 0.19306600000000002,
            "participating_rungs": [
                "A",
                "B",
                "D"
            ],
            "skipped_rungs": [],
            "depleted_rungs": [],
            "out_of_range_rungs": [
                "C",
                "S1",
                "S2",
                "S3"
            ]
        },
        {
            "timestamp": "2026-04-27T10:41:42.000Z",
            "trade_price": 1.0027513756878441,
            "price_source": "widest_matching_rung_fill",
            "volume_usd": 0.3727965636,
            "fees_usd": 0.000186,
            "participating_rungs": [
                "A",
                "B",
                "D"
            ],
            "skipped_rungs": [],
            "depleted_rungs": [],
            "out_of_range_rungs": [
                "C",
                "S1",
                "S2",
                "S3"
            ]
        },
        {
            "timestamp": "2026-04-27T10:43:00.000Z",
            "trade_price": 1.0025351136360106,
            "price_source": "widest_matching_rung_fill",
            "volume_usd": 3046.3830277629,
            "fees_usd": 1.520297,
            "participating_rungs": [
                "A",
                "B",
                "D"
            ],
            "skipped_rungs": [],
            "depleted_rungs": [],
            "out_of_range_rungs": [
                "C",
                "S1",
                "S2",
                "S3"
            ]
        },
        {
            "timestamp": "2026-04-27T10:44:24.000Z",
            "trade_price": 1.0021964784124497,
            "price_source": "widest_matching_rung_fill",
            "volume_usd": 1586.365881881,
            "fees_usd": 0.7919619999999999,
            "participating_rungs": [
                "A",
                "B",
                "C",
                "D"
            ],
            "skipped_rungs": [],
            "depleted_rungs": [],
            "out_of_range_rungs": [
                "S1",
                "S2",
                "S3"
            ]
        },
        {
            "timestamp": "2026-04-27T10:45:54.000Z",
            "trade_price": 1.0021047188067027,
            "price_source": "widest_matching_rung_fill",
            "volume_usd": 344.6734121346,
            "fees_usd": 0.17277599999999999,
            "participating_rungs": [
                "A",
                "B",
                "C",
                "D"
            ],
            "skipped_rungs": [],
            "depleted_rungs": [],
            "out_of_range_rungs": [
                "S1",
                "S2",
                "S3"
            ]
        },
        {
            "timestamp": "2026-04-27T10:46:06.000Z",
            "trade_price": 1.0022511255627815,
            "price_source": "widest_matching_rung_fill",
            "volume_usd": 0.3104767672,
            "fees_usd": 0.000155,
            "participating_rungs": [
                "A",
                "B",
                "D"
            ],
            "skipped_rungs": [],
            "depleted_rungs": [],
            "out_of_range_rungs": [
                "C",
                "S1",
                "S2",
                "S3"
            ]
        },
        {
            "timestamp": "2026-04-27T10:47:30.000Z",
            "trade_price": 1.0022511255627815,
            "price_source": "widest_matching_rung_fill",
            "volume_usd": 0.3605539151,
            "fees_usd": 0.00018,
            "participating_rungs": [
                "A",
                "B",
                "D"
            ],
            "skipped_rungs": [],
            "depleted_rungs": [],
            "out_of_range_rungs": [
                "C",
                "S1",
                "S2",
                "S3"
            ]
        },
        {
            "timestamp": "2026-04-27T10:55:24.000Z",
            "trade_price": 1.002111355166261,
            "price_source": "widest_matching_rung_fill",
            "volume_usd": 217.20439357510003,
            "fees_usd": 0.10844,
            "participating_rungs": [
                "A",
                "B",
                "C",
                "D"
            ],
            "skipped_rungs": [],
            "depleted_rungs": [],
            "out_of_range_rungs": [
                "S1",
                "S2",
                "S3"
            ]
        },
        {
            "timestamp": "2026-04-27T11:02:18.000Z",
            "trade_price": 1.002099542355261,
            "price_source": "widest_matching_rung_fill",
            "volume_usd": 54.7356988654,
            "fees_usd": 0.027439,
            "participating_rungs": [
                "A",
                "B",
                "C",
                "D"
            ],
            "skipped_rungs": [],
            "depleted_rungs": [],
            "out_of_range_rungs": [
                "S1",
                "S2",
                "S3"
            ]
        },
        {
            "timestamp": "2026-04-27T11:02:30.000Z",
            "trade_price": 1.0020010005002502,
            "price_source": "widest_matching_rung_fill",
            "volume_usd": 0.278389109,
            "fees_usd": 0.000139,
            "participating_rungs": [
                "A",
                "B",
                "D"
            ],
            "skipped_rungs": [
                "C"
            ],
            "depleted_rungs": [],
            "out_of_range_rungs": [
                "S1",
                "S2",
                "S3"
            ]
        },
        {
            "timestamp": "2026-04-27T11:51:54.000Z",
            "trade_price": 1.0017919853801294,
            "price_source": "widest_matching_rung_fill",
            "volume_usd": 5864.0377835966,
            "fees_usd": 2.928625,
            "participating_rungs": [
                "A",
                "B",
                "C",
                "D"
            ],
            "skipped_rungs": [],
            "depleted_rungs": [],
            "out_of_range_rungs": [
                "S1",
                "S2",
                "S3"
            ]
        },
        {
            "timestamp": "2026-04-27T12:02:42.000Z",
            "trade_price": 1.001535675263358,
            "price_source": "widest_matching_rung_fill",
            "volume_usd": 1019.8324639392,
            "fees_usd": 0.510958,
            "participating_rungs": [
                "A",
                "B",
                "C",
                "D"
            ],
            "skipped_rungs": [],
            "depleted_rungs": [],
            "out_of_range_rungs": [
                "S1",
                "S2",
                "S3"
            ]
        },
        {
            "timestamp": "2026-04-27T12:02:54.000Z",
            "trade_price": 1.0016675004168751,
            "price_source": "widest_matching_rung_fill",
            "volume_usd": 0.4624333809,
            "fees_usd": 0.000231,
            "participating_rungs": [
                "A",
                "B",
                "C",
                "D"
            ],
            "skipped_rungs": [],
            "depleted_rungs": [],
            "out_of_range_rungs": [
                "S1",
                "S2",
                "S3"
            ]
        },
        {
            "timestamp": "2026-04-27T12:57:42.000Z",
            "trade_price": 1.0015007503751876,
            "price_source": "widest_matching_rung_fill",
            "volume_usd": 0.6025761556,
            "fees_usd": 0.000301,
            "participating_rungs": [
                "A",
                "B",
                "C",
                "D"
            ],
            "skipped_rungs": [],
            "depleted_rungs": [],
            "out_of_range_rungs": [
                "S1",
                "S2",
                "S3"
            ]
        },
        {
            "timestamp": "2026-04-27T13:07:12.000Z",
            "trade_price": 1.0013952100054067,
            "price_source": "widest_matching_rung_fill",
            "volume_usd": 4007.7793471353,
            "fees_usd": 2.002348,
            "participating_rungs": [
                "A",
                "B",
                "C",
                "D",
                "S3"
            ],
            "skipped_rungs": [],
            "depleted_rungs": [],
            "out_of_range_rungs": [
                "S1",
                "S2"
            ]
        },
        {
            "timestamp": "2026-04-27T13:15:18.000Z",
            "trade_price": 1.0012506253126563,
            "price_source": "widest_matching_rung_fill",
            "volume_usd": 0.7905042923000001,
            "fees_usd": 0.00039500000000000006,
            "participating_rungs": [
                "A",
                "B",
                "C",
                "D",
                "S3"
            ],
            "skipped_rungs": [],
            "depleted_rungs": [],
            "out_of_range_rungs": [
                "S1",
                "S2"
            ]
        },
        {
            "timestamp": "2026-04-27T13:24:24.000Z",
            "trade_price": 1.0012506253126563,
            "price_source": "widest_matching_rung_fill",
            "volume_usd": 0.5723238513,
            "fees_usd": 0.000286,
            "participating_rungs": [
                "A",
                "B",
                "C",
                "D",
                "S3"
            ],
            "skipped_rungs": [],
            "depleted_rungs": [],
            "out_of_range_rungs": [
                "S1",
                "S2"
            ]
        },
        {
            "timestamp": "2026-04-27T13:40:24.000Z",
            "trade_price": 1.0011672502918125,
            "price_source": "widest_matching_rung_fill",
            "volume_usd": 0.7603932318,
            "fees_usd": 0.00038,
            "participating_rungs": [
                "A",
                "B",
                "C",
                "D",
                "S2",
                "S3"
            ],
            "skipped_rungs": [],
            "depleted_rungs": [],
            "out_of_range_rungs": [
                "S1"
            ]
        },
        {
            "timestamp": "2026-04-27T13:54:54.001Z",
            "trade_price": 1.0011006266242246,
            "price_source": "widest_matching_rung_fill",
            "volume_usd": 2724.1758301689,
            "fees_usd": 1.3615340000000002,
            "participating_rungs": [
                "A",
                "B",
                "C",
                "D",
                "S2",
                "S3"
            ],
            "skipped_rungs": [],
            "depleted_rungs": [],
            "out_of_range_rungs": [
                "S1"
            ]
        },
        {
            "timestamp": "2026-04-27T14:39:54.000Z",
            "trade_price": 1.001000500250125,
            "price_source": "widest_matching_rung_fill",
            "volume_usd": 5.1300533925,
            "fees_usd": 0.0025640000000000003,
            "participating_rungs": [
                "A",
                "B",
                "C",
                "D",
                "S1",
                "S2",
                "S3"
            ],
            "skipped_rungs": [],
            "depleted_rungs": [],
            "out_of_range_rungs": []
        },
        {
            "timestamp": "2026-04-27T15:04:24.000Z",
            "trade_price": 1.0010005002501252,
            "price_source": "widest_matching_rung_fill",
            "volume_usd": 0.7843033571,
            "fees_usd": 0.000392,
            "participating_rungs": [
                "A",
                "B",
                "C",
                "D",
                "S1",
                "S2",
                "S3"
            ],
            "skipped_rungs": [],
            "depleted_rungs": [],
            "out_of_range_rungs": []
        },
        {
            "timestamp": "2026-04-27T15:24:36.000Z",
            "trade_price": 1.0010005002501252,
            "price_source": "widest_matching_rung_fill",
            "volume_usd": 1.394209434,
            "fees_usd": 0.000697,
            "participating_rungs": [
                "A",
                "B",
                "C",
                "D",
                "S1",
                "S2",
                "S3"
            ],
            "skipped_rungs": [],
            "depleted_rungs": [],
            "out_of_range_rungs": []
        },
        {
            "timestamp": "2026-04-27T15:29:00.000Z",
            "trade_price": 1.0010005002501252,
            "price_source": "widest_matching_rung_fill",
            "volume_usd": 1.7425383113,
            "fees_usd": 0.000871,
            "participating_rungs": [
                "A",
                "B",
                "C",
                "D",
                "S1",
                "S2",
                "S3"
            ],
            "skipped_rungs": [],
            "depleted_rungs": [],
            "out_of_range_rungs": []
        },
        {
            "timestamp": "2026-04-27T15:44:48.000Z",
            "trade_price": 1.0009503328410427,
            "price_source": "widest_matching_rung_fill",
            "volume_usd": 1854.3460442138003,
            "fees_usd": 0.92685,
            "participating_rungs": [
                "A",
                "B",
                "C",
                "D",
                "S1",
                "S2",
                "S3"
            ],
            "skipped_rungs": [],
            "depleted_rungs": [],
            "out_of_range_rungs": []
        },
        {
            "timestamp": "2026-04-27T15:54:48.000Z",
            "trade_price": 1.0007504115060288,
            "price_source": "widest_matching_rung_fill",
            "volume_usd": 5591.1219531162,
            "fees_usd": 2.795526,
            "participating_rungs": [
                "A",
                "B",
                "C",
                "D",
                "S1",
                "S2",
                "S3"
            ],
            "skipped_rungs": [],
            "depleted_rungs": [],
            "out_of_range_rungs": []
        },
        {
            "timestamp": "2026-04-27T15:54:54.000Z",
            "trade_price": 1.0005502533496713,
            "price_source": "widest_matching_rung_fill",
            "volume_usd": 1363.6503145335,
            "fees_usd": 0.681953,
            "participating_rungs": [
                "A",
                "B",
                "C",
                "D",
                "S1",
                "S2",
                "S3"
            ],
            "skipped_rungs": [],
            "depleted_rungs": [],
            "out_of_range_rungs": []
        }
    ]
}
