{
    "version": 2,
    "generated_at": "2026-05-02T08:18:52+00:00",
    "meta": {
        "as_of_date": "2026-05-02",
        "pair": "USDT/USDC",
        "analysis_window_start": "2026-04-15T00:00:00Z",
        "source_window": {
            "start": "2026-04-15T00:00:00Z",
            "end": "2026-05-02T23:59:59Z"
        },
        "active_rung_count": 7,
        "total_trs_in_scope": 688
    },
    "portfolio": {
        "portfolio_value": 61088.05,
        "borrowed": {
            "USDT": 34426.1,
            "USDC": 18856.04
        },
        "borrow_rates_annual": {
            "USDT": 0.038,
            "USDC": 0.038
        },
        "total_fees_to_date": 567.2999649999999
    },
    "active_rungs": [
        {
            "rung": "A",
            "name": "Core",
            "created_at": "2026-04-14T22:50:30Z",
            "range_lower": 0.9979023082300623,
            "range_upper": 1.002904063656376,
            "target_allocation_pct": 46,
            "rung_value": 27600,
            "fees_to_date": 263.38169000000005,
            "fee_share_pct": 46.42723536921073,
            "efficiency_ratio": 1.0092877254176245,
            "eligible_trs": 688,
            "trades": 454,
            "skipped_count": 7,
            "out_of_range_count": 227,
            "depleted_count": 0,
            "utilization_pct": 65.98837209302324,
            "skipped_pct": 1.0174418604651163,
            "out_of_range_pct": 32.99418604651162,
            "depleted_pct": 0,
            "filled_volume_usd": 526433.2736862438,
            "active_days": 15,
            "average_active_capital": 25202.376,
            "capital_days": 378035.64,
            "apr_gross": 0.2542996127296358,
            "predicted_daily_income": 17.558779333333337,
            "predicted_monthly_income": 534.0795380555556,
            "predicted_yearly_income": 6408.954456666668,
            "stability_label": "normal"
        },
        {
            "rung": "B",
            "name": "Buffer",
            "created_at": "2026-04-14T22:50:30Z",
            "range_lower": 0.997403506726374,
            "range_upper": 1.00340561598864,
            "target_allocation_pct": 28,
            "rung_value": 16800,
            "fees_to_date": 135.66080599999998,
            "fee_share_pct": 23.913416952176263,
            "efficiency_ratio": 0.8540506054348665,
            "eligible_trs": 688,
            "trades": 544,
            "skipped_count": 6,
            "out_of_range_count": 138,
            "depleted_count": 0,
            "utilization_pct": 79.06976744186046,
            "skipped_pct": 0.872093023255814,
            "out_of_range_pct": 20.058139534883722,
            "depleted_pct": 0,
            "filled_volume_usd": 271155.4626033774,
            "active_days": 15,
            "average_active_capital": 11795.264000000001,
            "capital_days": 176928.96000000002,
            "apr_gross": 0.27986483495974873,
            "predicted_daily_income": 9.044053733333332,
            "predicted_monthly_income": 275.0899677222222,
            "predicted_yearly_income": 3301.079612666666,
            "stability_label": "normal"
        },
        {
            "rung": "C",
            "name": "Scalp",
            "created_at": "2026-04-14T22:50:30Z",
            "range_lower": 0.9988007796361366,
            "range_upper": 1.0021021013305984,
            "target_allocation_pct": 8,
            "rung_value": 4800,
            "fees_to_date": 75.30763800000003,
            "fee_share_pct": 13.274747513865973,
            "efficiency_ratio": 1.6593434392332467,
            "eligible_trs": 688,
            "trades": 320,
            "skipped_count": 15,
            "out_of_range_count": 353,
            "depleted_count": 0,
            "utilization_pct": 46.51162790697674,
            "skipped_pct": 2.1802325581395348,
            "out_of_range_pct": 51.30813953488372,
            "depleted_pct": 0,
            "filled_volume_usd": 150509.90437024977,
            "active_days": 15,
            "average_active_capital": 7254.736672533335,
            "capital_days": 108821.05008800002,
            "apr_gross": 0.25259164332426437,
            "predicted_daily_income": 5.020509200000002,
            "predicted_monthly_income": 152.7071548333334,
            "predicted_yearly_income": 1832.4858580000007,
            "stability_label": "normal"
        },
        {
            "rung": "D",
            "name": "Catch-all",
            "created_at": "2026-04-15T16:17:30Z",
            "range_lower": 0.996406651572219,
            "range_upper": 1.0054143348356561,
            "target_allocation_pct": 2,
            "rung_value": 1200,
            "fees_to_date": 10.291950999999997,
            "fee_share_pct": 1.8141991247963496,
            "efficiency_ratio": 0.9070995623981748,
            "eligible_trs": 644,
            "trades": 616,
            "skipped_count": 28,
            "out_of_range_count": 0,
            "depleted_count": 0,
            "utilization_pct": 95.65217391304348,
            "skipped_pct": 4.3478260869565215,
            "out_of_range_pct": 0,
            "depleted_pct": 0,
            "filled_volume_usd": 20572.0421826362,
            "active_days": 15,
            "average_active_capital": 900.3449736,
            "capital_days": 13505.174604,
            "apr_gross": 0.278157241587041,
            "predicted_daily_income": 0.6861300666666665,
            "predicted_monthly_income": 20.869789527777773,
            "predicted_yearly_income": 250.43747433333328,
            "stability_label": "normal"
        },
        {
            "rung": "S1",
            "name": "Tick",
            "created_at": "2026-04-16T19:58:48Z",
            "range_lower": 1.0006001500200015,
            "range_upper": 1.001000450120021,
            "target_allocation_pct": 3,
            "rung_value": 2888.05,
            "fees_to_date": 25.582128,
            "fee_share_pct": 4.509453477579538,
            "efficiency_ratio": 1.5031511591931794,
            "eligible_trs": 620,
            "trades": 84,
            "skipped_count": 0,
            "out_of_range_count": 536,
            "depleted_count": 0,
            "utilization_pct": 13.548387096774196,
            "skipped_pct": 0,
            "out_of_range_pct": 86.45161290322581,
            "depleted_pct": 0,
            "filled_volume_usd": 51117.8381836832,
            "active_days": 14,
            "average_active_capital": 2143.3211842857136,
            "capital_days": 30006.49657999999,
            "apr_gross": 0.3111818367434351,
            "predicted_daily_income": 1.827294857142857,
            "predicted_monthly_income": 55.58021857142857,
            "predicted_yearly_income": 666.9626228571428,
            "stability_label": "normal"
        },
        {
            "rung": "S2",
            "name": "Flow",
            "created_at": "2026-04-16T19:58:48Z",
            "range_lower": 1.000400060004,
            "range_upper": 1.0012006602200494,
            "target_allocation_pct": 6.5,
            "rung_value": 3900,
            "fees_to_date": 28.105503,
            "fee_share_pct": 4.954257841352062,
            "efficiency_ratio": 0.7621935140541634,
            "eligible_trs": 620,
            "trades": 131,
            "skipped_count": 4,
            "out_of_range_count": 485,
            "depleted_count": 0,
            "utilization_pct": 21.129032258064516,
            "skipped_pct": 0.6451612903225806,
            "out_of_range_pct": 78.2258064516129,
            "depleted_pct": 0,
            "filled_volume_usd": 56162.224981345906,
            "active_days": 14,
            "average_active_capital": 2287.1228612857144,
            "capital_days": 32019.720058,
            "apr_gross": 0.3203809582475395,
            "predicted_daily_income": 2.0075359285714285,
            "predicted_monthly_income": 61.062551160714285,
            "predicted_yearly_income": 732.7506139285714,
            "stability_label": "normal"
        },
        {
            "rung": "S3",
            "name": "Sweep",
            "created_at": "2026-04-16T19:58:48Z",
            "range_lower": 1.00020001,
            "range_upper": 1.0014009103641,
            "target_allocation_pct": 6.5,
            "rung_value": 3900,
            "fees_to_date": 28.970249000000003,
            "fee_share_pct": 5.10668972101911,
            "efficiency_ratio": 0.7856445724644784,
            "eligible_trs": 620,
            "trades": 161,
            "skipped_count": 3,
            "out_of_range_count": 456,
            "depleted_count": 0,
            "utilization_pct": 25.967741935483872,
            "skipped_pct": 0.4838709677419355,
            "out_of_range_pct": 73.54838709677419,
            "depleted_pct": 0,
            "filled_volume_usd": 57891.9865455745,
            "active_days": 14,
            "average_active_capital": 2380.584919285714,
            "capital_days": 33328.18887,
            "apr_gross": 0.3172731925591732,
            "predicted_daily_income": 2.0693035,
            "predicted_monthly_income": 62.94131479166668,
            "predicted_yearly_income": 755.2957775000001,
            "stability_label": "normal"
        }
    ],
    "recent_daily": [
        {
            "date": "2026-04-23",
            "total_fees": 25.567253,
            "trs": 16
        },
        {
            "date": "2026-04-24",
            "total_fees": 0.095956,
            "trs": 2
        },
        {
            "date": "2026-04-26",
            "total_fees": 28.459167,
            "trs": 17
        },
        {
            "date": "2026-04-27",
            "total_fees": 34.940550000000016,
            "trs": 69
        },
        {
            "date": "2026-04-28",
            "total_fees": 115.158346,
            "trs": 125
        },
        {
            "date": "2026-04-29",
            "total_fees": 65.93944499999999,
            "trs": 83
        },
        {
            "date": "2026-05-02",
            "total_fees": 18.93798600000001,
            "trs": 27
        }
    ],
    "bucket_summary": [
        {
            "price_bucket_low": 1,
            "price_bucket_high": 1.0005,
            "tr_count": 1,
            "total_volume_usd": 5592.4428441547,
            "rung_counts": {
                "A": {
                    "participating": 1,
                    "skipped": 0,
                    "depleted": 0,
                    "out_of_range": 0
                },
                "B": {
                    "participating": 1,
                    "skipped": 0,
                    "depleted": 0,
                    "out_of_range": 0
                },
                "C": {
                    "participating": 1,
                    "skipped": 0,
                    "depleted": 0,
                    "out_of_range": 0
                },
                "D": {
                    "participating": 1,
                    "skipped": 0,
                    "depleted": 0,
                    "out_of_range": 0
                },
                "S1": {
                    "participating": 1,
                    "skipped": 0,
                    "depleted": 0,
                    "out_of_range": 0
                },
                "S2": {
                    "participating": 1,
                    "skipped": 0,
                    "depleted": 0,
                    "out_of_range": 0
                },
                "S3": {
                    "participating": 1,
                    "skipped": 0,
                    "depleted": 0,
                    "out_of_range": 0
                }
            }
        },
        {
            "price_bucket_low": 1.0005,
            "price_bucket_high": 1.001,
            "tr_count": 2,
            "total_volume_usd": 7821.3626201094,
            "rung_counts": {
                "A": {
                    "participating": 2,
                    "skipped": 0,
                    "depleted": 0,
                    "out_of_range": 0
                },
                "B": {
                    "participating": 2,
                    "skipped": 0,
                    "depleted": 0,
                    "out_of_range": 0
                },
                "C": {
                    "participating": 2,
                    "skipped": 0,
                    "depleted": 0,
                    "out_of_range": 0
                },
                "D": {
                    "participating": 2,
                    "skipped": 0,
                    "depleted": 0,
                    "out_of_range": 0
                },
                "S1": {
                    "participating": 2,
                    "skipped": 0,
                    "depleted": 0,
                    "out_of_range": 0
                },
                "S2": {
                    "participating": 2,
                    "skipped": 0,
                    "depleted": 0,
                    "out_of_range": 0
                },
                "S3": {
                    "participating": 2,
                    "skipped": 0,
                    "depleted": 0,
                    "out_of_range": 0
                }
            }
        },
        {
            "price_bucket_low": 1.0010000000000001,
            "price_bucket_high": 1.0015,
            "tr_count": 1,
            "total_volume_usd": 0.034011033,
            "rung_counts": {
                "A": {
                    "participating": 1,
                    "skipped": 0,
                    "depleted": 0,
                    "out_of_range": 0
                },
                "B": {
                    "participating": 1,
                    "skipped": 0,
                    "depleted": 0,
                    "out_of_range": 0
                },
                "C": {
                    "participating": 1,
                    "skipped": 0,
                    "depleted": 0,
                    "out_of_range": 0
                },
                "D": {
                    "participating": 0,
                    "skipped": 1,
                    "depleted": 0,
                    "out_of_range": 0
                },
                "S1": {
                    "participating": 1,
                    "skipped": 0,
                    "depleted": 0,
                    "out_of_range": 0
                },
                "S2": {
                    "participating": 1,
                    "skipped": 0,
                    "depleted": 0,
                    "out_of_range": 0
                },
                "S3": {
                    "participating": 1,
                    "skipped": 0,
                    "depleted": 0,
                    "out_of_range": 0
                }
            }
        },
        {
            "price_bucket_low": 1.0015,
            "price_bucket_high": 1.002,
            "tr_count": 1,
            "total_volume_usd": 18075.066555503498,
            "rung_counts": {
                "A": {
                    "participating": 1,
                    "skipped": 0,
                    "depleted": 0,
                    "out_of_range": 0
                },
                "B": {
                    "participating": 1,
                    "skipped": 0,
                    "depleted": 0,
                    "out_of_range": 0
                },
                "C": {
                    "participating": 1,
                    "skipped": 0,
                    "depleted": 0,
                    "out_of_range": 0
                },
                "D": {
                    "participating": 1,
                    "skipped": 0,
                    "depleted": 0,
                    "out_of_range": 0
                },
                "S1": {
                    "participating": 1,
                    "skipped": 0,
                    "depleted": 0,
                    "out_of_range": 0
                },
                "S2": {
                    "participating": 1,
                    "skipped": 0,
                    "depleted": 0,
                    "out_of_range": 0
                },
                "S3": {
                    "participating": 1,
                    "skipped": 0,
                    "depleted": 0,
                    "out_of_range": 0
                }
            }
        },
        {
            "price_bucket_low": 1.0025,
            "price_bucket_high": 1.003,
            "tr_count": 7,
            "total_volume_usd": 775.2901921768,
            "rung_counts": {
                "A": {
                    "participating": 6,
                    "skipped": 0,
                    "depleted": 0,
                    "out_of_range": 1
                },
                "B": {
                    "participating": 7,
                    "skipped": 0,
                    "depleted": 0,
                    "out_of_range": 0
                },
                "C": {
                    "participating": 0,
                    "skipped": 0,
                    "depleted": 0,
                    "out_of_range": 7
                },
                "D": {
                    "participating": 5,
                    "skipped": 2,
                    "depleted": 0,
                    "out_of_range": 0
                },
                "S1": {
                    "participating": 0,
                    "skipped": 0,
                    "depleted": 0,
                    "out_of_range": 7
                },
                "S2": {
                    "participating": 0,
                    "skipped": 0,
                    "depleted": 0,
                    "out_of_range": 7
                },
                "S3": {
                    "participating": 0,
                    "skipped": 0,
                    "depleted": 0,
                    "out_of_range": 7
                }
            }
        },
        {
            "price_bucket_low": 1.0035,
            "price_bucket_high": 1.004,
            "tr_count": 7,
            "total_volume_usd": 4570.905316738099,
            "rung_counts": {
                "A": {
                    "participating": 1,
                    "skipped": 0,
                    "depleted": 0,
                    "out_of_range": 6
                },
                "B": {
                    "participating": 7,
                    "skipped": 0,
                    "depleted": 0,
                    "out_of_range": 0
                },
                "C": {
                    "participating": 0,
                    "skipped": 0,
                    "depleted": 0,
                    "out_of_range": 7
                },
                "D": {
                    "participating": 7,
                    "skipped": 0,
                    "depleted": 0,
                    "out_of_range": 0
                },
                "S1": {
                    "participating": 0,
                    "skipped": 0,
                    "depleted": 0,
                    "out_of_range": 7
                },
                "S2": {
                    "participating": 0,
                    "skipped": 0,
                    "depleted": 0,
                    "out_of_range": 7
                },
                "S3": {
                    "participating": 0,
                    "skipped": 0,
                    "depleted": 0,
                    "out_of_range": 7
                }
            }
        },
        {
            "price_bucket_low": 1.004,
            "price_bucket_high": 1.0045,
            "tr_count": 3,
            "total_volume_usd": 0.1023780418,
            "rung_counts": {
                "A": {
                    "participating": 0,
                    "skipped": 0,
                    "depleted": 0,
                    "out_of_range": 3
                },
                "B": {
                    "participating": 0,
                    "skipped": 0,
                    "depleted": 0,
                    "out_of_range": 3
                },
                "C": {
                    "participating": 0,
                    "skipped": 0,
                    "depleted": 0,
                    "out_of_range": 3
                },
                "D": {
                    "participating": 3,
                    "skipped": 0,
                    "depleted": 0,
                    "out_of_range": 0
                },
                "S1": {
                    "participating": 0,
                    "skipped": 0,
                    "depleted": 0,
                    "out_of_range": 3
                },
                "S2": {
                    "participating": 0,
                    "skipped": 0,
                    "depleted": 0,
                    "out_of_range": 3
                },
                "S3": {
                    "participating": 0,
                    "skipped": 0,
                    "depleted": 0,
                    "out_of_range": 3
                }
            }
        },
        {
            "price_bucket_low": 1.0030000000000001,
            "price_bucket_high": 1.0035,
            "tr_count": 5,
            "total_volume_usd": 966.2024599999002,
            "rung_counts": {
                "A": {
                    "participating": 2,
                    "skipped": 0,
                    "depleted": 0,
                    "out_of_range": 3
                },
                "B": {
                    "participating": 5,
                    "skipped": 0,
                    "depleted": 0,
                    "out_of_range": 0
                },
                "C": {
                    "participating": 0,
                    "skipped": 0,
                    "depleted": 0,
                    "out_of_range": 5
                },
                "D": {
                    "participating": 5,
                    "skipped": 0,
                    "depleted": 0,
                    "out_of_range": 0
                },
                "S1": {
                    "participating": 0,
                    "skipped": 0,
                    "depleted": 0,
                    "out_of_range": 5
                },
                "S2": {
                    "participating": 0,
                    "skipped": 0,
                    "depleted": 0,
                    "out_of_range": 5
                },
                "S3": {
                    "participating": 0,
                    "skipped": 0,
                    "depleted": 0,
                    "out_of_range": 5
                }
            }
        }
    ],
    "alerts": [],
    "recent_tr_examples": [
        {
            "timestamp": "2026-04-29T07:19:24.000Z",
            "trade_price": 1.0029014507253626,
            "price_source": "widest_matching_rung_fill",
            "volume_usd": 0.2425427238,
            "fees_usd": 0.000121,
            "participating_rungs": [
                "B",
                "D"
            ],
            "skipped_rungs": [
                "A"
            ],
            "depleted_rungs": [],
            "out_of_range_rungs": [
                "C",
                "S1",
                "S2",
                "S3"
            ]
        },
        {
            "timestamp": "2026-04-29T07:20:00.000Z",
            "trade_price": 1.0029181257295314,
            "price_source": "widest_matching_rung_fill",
            "volume_usd": 0.2405345509,
            "fees_usd": 0.00012,
            "participating_rungs": [
                "B",
                "D"
            ],
            "skipped_rungs": [],
            "depleted_rungs": [],
            "out_of_range_rungs": [
                "A",
                "C",
                "S1",
                "S2",
                "S3"
            ]
        },
        {
            "timestamp": "2026-04-29T07:23:12.000Z",
            "trade_price": 1.0029048990395957,
            "price_source": "widest_matching_rung_fill",
            "volume_usd": 345.0560444407,
            "fees_usd": 0.172152,
            "participating_rungs": [
                "A",
                "B",
                "D"
            ],
            "skipped_rungs": [],
            "depleted_rungs": [],
            "out_of_range_rungs": [
                "C",
                "S1",
                "S2",
                "S3"
            ]
        },
        {
            "timestamp": "2026-04-29T07:25:36.000Z",
            "trade_price": 1.0028156256396885,
            "price_source": "widest_matching_rung_fill",
            "volume_usd": 988.8933875985,
            "fees_usd": 0.493408,
            "participating_rungs": [
                "A",
                "B",
                "D"
            ],
            "skipped_rungs": [],
            "depleted_rungs": [],
            "out_of_range_rungs": [
                "C",
                "S1",
                "S2",
                "S3"
            ]
        },
        {
            "timestamp": "2026-04-29T07:30:24.001Z",
            "trade_price": 1.0028304932832854,
            "price_source": "widest_matching_rung_fill",
            "volume_usd": 1236.4374522012,
            "fees_usd": 0.6203879999999999,
            "participating_rungs": [
                "A",
                "B",
                "D"
            ],
            "skipped_rungs": [],
            "depleted_rungs": [],
            "out_of_range_rungs": [
                "C",
                "S1",
                "S2",
                "S3"
            ]
        },
        {
            "timestamp": "2026-04-29T07:30:36.000Z",
            "trade_price": 1.0030015007503752,
            "price_source": "widest_matching_rung_fill",
            "volume_usd": 0.1824055846,
            "fees_usd": 9.1e-5,
            "participating_rungs": [
                "A",
                "B",
                "D"
            ],
            "skipped_rungs": [],
            "depleted_rungs": [],
            "out_of_range_rungs": [
                "C",
                "S1",
                "S2",
                "S3"
            ]
        },
        {
            "timestamp": "2026-04-29T07:38:24.000Z",
            "trade_price": 1.0028829123594285,
            "price_source": "widest_matching_rung_fill",
            "volume_usd": 355.6744587515,
            "fees_usd": 0.17745,
            "participating_rungs": [
                "A",
                "B",
                "D"
            ],
            "skipped_rungs": [],
            "depleted_rungs": [],
            "out_of_range_rungs": [
                "C",
                "S1",
                "S2",
                "S3"
            ]
        },
        {
            "timestamp": "2026-04-29T07:39:54.000Z",
            "trade_price": 1.0030015007503752,
            "price_source": "widest_matching_rung_fill",
            "volume_usd": 0.20243130239999998,
            "fees_usd": 0.000101,
            "participating_rungs": [
                "A",
                "B",
                "D"
            ],
            "skipped_rungs": [],
            "depleted_rungs": [],
            "out_of_range_rungs": [
                "C",
                "S1",
                "S2",
                "S3"
            ]
        },
        {
            "timestamp": "2026-04-29T08:09:48.000Z",
            "trade_price": 1.00285003702626,
            "price_source": "widest_matching_rung_fill",
            "volume_usd": 196.75966614010002,
            "fees_usd": 0.09817199999999998,
            "participating_rungs": [
                "A",
                "B",
                "D"
            ],
            "skipped_rungs": [],
            "depleted_rungs": [],
            "out_of_range_rungs": [
                "C",
                "S1",
                "S2",
                "S3"
            ]
        },
        {
            "timestamp": "2026-04-29T09:00:06.000Z",
            "trade_price": 1.0030216209005969,
            "price_source": "widest_matching_rung_fill",
            "volume_usd": 1431.1887455941,
            "fees_usd": 0.7182499999999999,
            "participating_rungs": [
                "A",
                "B",
                "D"
            ],
            "skipped_rungs": [],
            "depleted_rungs": [],
            "out_of_range_rungs": [
                "C",
                "S1",
                "S2",
                "S3"
            ]
        },
        {
            "timestamp": "2026-04-29T09:00:18.000Z",
            "trade_price": 1.0036268134067032,
            "price_source": "widest_matching_rung_fill",
            "volume_usd": 679.9283553416,
            "fees_usd": 0.341441,
            "participating_rungs": [
                "B",
                "D"
            ],
            "skipped_rungs": [],
            "depleted_rungs": [],
            "out_of_range_rungs": [
                "A",
                "C",
                "S1",
                "S2",
                "S3"
            ]
        },
        {
            "timestamp": "2026-04-29T09:00:30.001Z",
            "trade_price": 1.004106219776555,
            "price_source": "widest_matching_rung_fill",
            "volume_usd": 0.2408264466,
            "fees_usd": 0.00012,
            "participating_rungs": [
                "D"
            ],
            "skipped_rungs": [],
            "depleted_rungs": [],
            "out_of_range_rungs": [
                "A",
                "B",
                "C",
                "S1",
                "S2",
                "S3"
            ]
        },
        {
            "timestamp": "2026-04-29T09:01:36.000Z",
            "trade_price": 1.003720687847976,
            "price_source": "widest_matching_rung_fill",
            "volume_usd": 299.8074009196,
            "fees_usd": 0.149443,
            "participating_rungs": [
                "B",
                "D"
            ],
            "skipped_rungs": [],
            "depleted_rungs": [],
            "out_of_range_rungs": [
                "A",
                "C",
                "S1",
                "S2",
                "S3"
            ]
        },
        {
            "timestamp": "2026-04-29T09:06:06.000Z",
            "trade_price": 1.0033016508254127,
            "price_source": "widest_matching_rung_fill",
            "volume_usd": 0.2205755545,
            "fees_usd": 0.00011,
            "participating_rungs": [
                "B",
                "D"
            ],
            "skipped_rungs": [],
            "depleted_rungs": [],
            "out_of_range_rungs": [
                "A",
                "C",
                "S1",
                "S2",
                "S3"
            ]
        },
        {
            "timestamp": "2026-04-29T09:09:24.000Z",
            "trade_price": 1.0027157372312865,
            "price_source": "widest_matching_rung_fill",
            "volume_usd": 8093.5604360051,
            "fees_usd": 4.038566,
            "participating_rungs": [
                "A",
                "B",
                "C",
                "D"
            ],
            "skipped_rungs": [],
            "depleted_rungs": [],
            "out_of_range_rungs": [
                "S1",
                "S2",
                "S3"
            ]
        },
        {
            "timestamp": "2026-04-29T09:09:30.000Z",
            "trade_price": 1.0016391577808794,
            "price_source": "widest_matching_rung_fill",
            "volume_usd": 9818.760309356103,
            "fees_usd": 4.904680999999999,
            "participating_rungs": [
                "A",
                "B",
                "C",
                "D",
                "S2",
                "S3"
            ],
            "skipped_rungs": [],
            "depleted_rungs": [],
            "out_of_range_rungs": [
                "S1"
            ]
        },
        {
            "timestamp": "2026-04-29T09:09:36.000Z",
            "trade_price": 1.0010411677399018,
            "price_source": "widest_matching_rung_fill",
            "volume_usd": 4905.257833484199,
            "fees_usd": 2.451745,
            "participating_rungs": [
                "A",
                "B",
                "C",
                "D",
                "S1",
                "S2",
                "S3"
            ],
            "skipped_rungs": [],
            "depleted_rungs": [],
            "out_of_range_rungs": []
        },
        {
            "timestamp": "2026-04-29T09:28:12.000Z",
            "trade_price": 1.00085044020362,
            "price_source": "widest_matching_rung_fill",
            "volume_usd": 2254.5656476714,
            "fees_usd": 1.127061,
            "participating_rungs": [
                "A",
                "B",
                "C",
                "D",
                "S1",
                "S2",
                "S3"
            ],
            "skipped_rungs": [],
            "depleted_rungs": [],
            "out_of_range_rungs": []
        },
        {
            "timestamp": "2026-04-29T09:28:18.000Z",
            "trade_price": 1.0007503751875937,
            "price_source": "widest_matching_rung_fill",
            "volume_usd": 2254.4602238223,
            "fees_usd": 1.127121,
            "participating_rungs": [
                "A",
                "B",
                "C",
                "D",
                "S1",
                "S2",
                "S3"
            ],
            "skipped_rungs": [],
            "depleted_rungs": [],
            "out_of_range_rungs": []
        },
        {
            "timestamp": "2026-04-29T09:28:30.000Z",
            "trade_price": 1.0006319757116007,
            "price_source": "widest_matching_rung_fill",
            "volume_usd": 2916.0994742356,
            "fees_usd": 1.4581380000000002,
            "participating_rungs": [
                "A",
                "B",
                "C",
                "D",
                "S1",
                "S2",
                "S3"
            ],
            "skipped_rungs": [],
            "depleted_rungs": [],
            "out_of_range_rungs": []
        },
        {
            "timestamp": "2026-04-29T09:28:36.000Z",
            "trade_price": 1.0005319519537494,
            "price_source": "widest_matching_rung_fill",
            "volume_usd": 1143.0045008827,
            "fees_usd": 0.5715939999999999,
            "participating_rungs": [
                "A",
                "B",
                "C",
                "D",
                "S2",
                "S3"
            ],
            "skipped_rungs": [],
            "depleted_rungs": [],
            "out_of_range_rungs": [
                "S1"
            ]
        },
        {
            "timestamp": "2026-04-29T09:28:48.000Z",
            "trade_price": 1.000450195139511,
            "price_source": "widest_matching_rung_fill",
            "volume_usd": 1804.0889956061,
            "fees_usd": 0.902263,
            "participating_rungs": [
                "A",
                "B",
                "C",
                "D",
                "S2",
                "S3"
            ],
            "skipped_rungs": [],
            "depleted_rungs": [],
            "out_of_range_rungs": [
                "S1"
            ]
        },
        {
            "timestamp": "2026-04-29T15:53:42.000Z",
            "trade_price": 1.0003501601010212,
            "price_source": "widest_matching_rung_fill",
            "volume_usd": 1317.2452305834001,
            "fees_usd": 0.658844,
            "participating_rungs": [
                "A",
                "B",
                "C",
                "D",
                "S2",
                "S3"
            ],
            "skipped_rungs": [],
            "depleted_rungs": [],
            "out_of_range_rungs": [
                "S1"
            ]
        },
        {
            "timestamp": "2026-05-02T01:23:06.001Z",
            "trade_price": 1.0004650700798625,
            "price_source": "widest_matching_rung_fill",
            "volume_usd": 5592.4428441547,
            "fees_usd": 2.799456,
            "participating_rungs": [
                "A",
                "B",
                "C",
                "D",
                "S1",
                "S2",
                "S3"
            ],
            "skipped_rungs": [],
            "depleted_rungs": [],
            "out_of_range_rungs": []
        },
        {
            "timestamp": "2026-05-02T01:51:24.000Z",
            "trade_price": 1.0008018493265134,
            "price_source": "widest_matching_rung_fill",
            "volume_usd": 7737.094794315,
            "fees_usd": 3.874329,
            "participating_rungs": [
                "A",
                "B",
                "C",
                "D",
                "S1",
                "S2",
                "S3"
            ],
            "skipped_rungs": [],
            "depleted_rungs": [],
            "out_of_range_rungs": []
        },
        {
            "timestamp": "2026-05-02T01:52:24.000Z",
            "trade_price": 1.0010005002501252,
            "price_source": "widest_matching_rung_fill",
            "volume_usd": 0.034011033,
            "fees_usd": 1.7e-5,
            "participating_rungs": [
                "A",
                "B",
                "C",
                "S1",
                "S2",
                "S3"
            ],
            "skipped_rungs": [
                "D"
            ],
            "depleted_rungs": [],
            "out_of_range_rungs": []
        },
        {
            "timestamp": "2026-05-02T02:01:48.001Z",
            "trade_price": 1.0009723737370693,
            "price_source": "widest_matching_rung_fill",
            "volume_usd": 84.2678257944,
            "fees_usd": 0.042123,
            "participating_rungs": [
                "A",
                "B",
                "C",
                "D",
                "S1",
                "S2",
                "S3"
            ],
            "skipped_rungs": [],
            "depleted_rungs": [],
            "out_of_range_rungs": []
        },
        {
            "timestamp": "2026-05-02T02:07:24.000Z",
            "trade_price": 1.0017863720981641,
            "price_source": "widest_matching_rung_fill",
            "volume_usd": 18075.066555503498,
            "fees_usd": 9.059868,
            "participating_rungs": [
                "A",
                "B",
                "C",
                "D",
                "S1",
                "S2",
                "S3"
            ],
            "skipped_rungs": [],
            "depleted_rungs": [],
            "out_of_range_rungs": []
        },
        {
            "timestamp": "2026-05-02T02:07:36.001Z",
            "trade_price": 1.0025012506253128,
            "price_source": "widest_matching_rung_fill",
            "volume_usd": 0.1582986668,
            "fees_usd": 7.9e-5,
            "participating_rungs": [
                "A",
                "B",
                "D"
            ],
            "skipped_rungs": [],
            "depleted_rungs": [],
            "out_of_range_rungs": [
                "C",
                "S1",
                "S2",
                "S3"
            ]
        },
        {
            "timestamp": "2026-05-02T02:07:42.001Z",
            "trade_price": 1.003505998412508,
            "price_source": "widest_matching_rung_fill",
            "volume_usd": 4131.208550114699,
            "fees_usd": 2.074274,
            "participating_rungs": [
                "A",
                "B",
                "D"
            ],
            "skipped_rungs": [],
            "depleted_rungs": [],
            "out_of_range_rungs": [
                "C",
                "S1",
                "S2",
                "S3"
            ]
        },
        {
            "timestamp": "2026-05-02T02:08:24.001Z",
            "trade_price": 1.004418876104719,
            "price_source": "widest_matching_rung_fill",
            "volume_usd": 0.0361336287,
            "fees_usd": 1.8e-5,
            "participating_rungs": [
                "D"
            ],
            "skipped_rungs": [],
            "depleted_rungs": [],
            "out_of_range_rungs": [
                "A",
                "B",
                "C",
                "S1",
                "S2",
                "S3"
            ]
        },
        {
            "timestamp": "2026-05-02T02:08:30.000Z",
            "trade_price": 1.0044139716917282,
            "price_source": "widest_matching_rung_fill",
            "volume_usd": 0.0341260383,
            "fees_usd": 1.7e-5,
            "participating_rungs": [
                "D"
            ],
            "skipped_rungs": [],
            "depleted_rungs": [],
            "out_of_range_rungs": [
                "A",
                "B",
                "C",
                "S1",
                "S2",
                "S3"
            ]
        },
        {
            "timestamp": "2026-05-02T02:09:24.000Z",
            "trade_price": 1.0044084542271137,
            "price_source": "widest_matching_rung_fill",
            "volume_usd": 0.0321183748,
            "fees_usd": 1.6e-5,
            "participating_rungs": [
                "D"
            ],
            "skipped_rungs": [],
            "depleted_rungs": [],
            "out_of_range_rungs": [
                "A",
                "B",
                "C",
                "S1",
                "S2",
                "S3"
            ]
        },
        {
            "timestamp": "2026-05-02T02:10:48.000Z",
            "trade_price": 1.003854838191675,
            "price_source": "widest_matching_rung_fill",
            "volume_usd": 439.48420847939997,
            "fees_usd": 0.219058,
            "participating_rungs": [
                "B",
                "D"
            ],
            "skipped_rungs": [],
            "depleted_rungs": [],
            "out_of_range_rungs": [
                "A",
                "C",
                "S1",
                "S2",
                "S3"
            ]
        },
        {
            "timestamp": "2026-05-02T02:14:00.000Z",
            "trade_price": 1.0035017508754378,
            "price_source": "widest_matching_rung_fill",
            "volume_usd": 0.0381003021,
            "fees_usd": 1.9e-5,
            "participating_rungs": [
                "B",
                "D"
            ],
            "skipped_rungs": [],
            "depleted_rungs": [],
            "out_of_range_rungs": [
                "A",
                "C",
                "S1",
                "S2",
                "S3"
            ]
        },
        {
            "timestamp": "2026-05-02T02:15:18.000Z",
            "trade_price": 1.0035017508754378,
            "price_source": "widest_matching_rung_fill",
            "volume_usd": 0.0401047579,
            "fees_usd": 2.0e-5,
            "participating_rungs": [
                "B",
                "D"
            ],
            "skipped_rungs": [],
            "depleted_rungs": [],
            "out_of_range_rungs": [
                "A",
                "C",
                "S1",
                "S2",
                "S3"
            ]
        },
        {
            "timestamp": "2026-05-02T02:23:54.001Z",
            "trade_price": 1.0035017508754378,
            "price_source": "widest_matching_rung_fill",
            "volume_usd": 0.0461211949,
            "fees_usd": 2.3e-5,
            "participating_rungs": [
                "B",
                "D"
            ],
            "skipped_rungs": [],
            "depleted_rungs": [],
            "out_of_range_rungs": [
                "A",
                "C",
                "S1",
                "S2",
                "S3"
            ]
        },
        {
            "timestamp": "2026-05-02T02:26:06.001Z",
            "trade_price": 1.0035017508754378,
            "price_source": "widest_matching_rung_fill",
            "volume_usd": 0.0461211011,
            "fees_usd": 2.3e-5,
            "participating_rungs": [
                "B",
                "D"
            ],
            "skipped_rungs": [],
            "depleted_rungs": [],
            "out_of_range_rungs": [
                "A",
                "C",
                "S1",
                "S2",
                "S3"
            ]
        },
        {
            "timestamp": "2026-05-02T02:26:36.001Z",
            "trade_price": 1.0035017508754378,
            "price_source": "widest_matching_rung_fill",
            "volume_usd": 0.042110788,
            "fees_usd": 2.1000000000000002e-5,
            "participating_rungs": [
                "B",
                "D"
            ],
            "skipped_rungs": [],
            "depleted_rungs": [],
            "out_of_range_rungs": [
                "A",
                "C",
                "S1",
                "S2",
                "S3"
            ]
        },
        {
            "timestamp": "2026-05-02T02:36:42.000Z",
            "trade_price": 1.0032540170658943,
            "price_source": "widest_matching_rung_fill",
            "volume_usd": 276.7488814368,
            "fees_usd": 0.138018,
            "participating_rungs": [
                "B",
                "D"
            ],
            "skipped_rungs": [],
            "depleted_rungs": [],
            "out_of_range_rungs": [
                "A",
                "C",
                "S1",
                "S2",
                "S3"
            ]
        },
        {
            "timestamp": "2026-05-02T02:40:12.000Z",
            "trade_price": 1.0030891797206734,
            "price_source": "widest_matching_rung_fill",
            "volume_usd": 689.2711800784,
            "fees_usd": 0.343793,
            "participating_rungs": [
                "B",
                "D"
            ],
            "skipped_rungs": [],
            "depleted_rungs": [],
            "out_of_range_rungs": [
                "A",
                "C",
                "S1",
                "S2",
                "S3"
            ]
        },
        {
            "timestamp": "2026-05-02T03:16:48.000Z",
            "trade_price": 1.0030015007503752,
            "price_source": "widest_matching_rung_fill",
            "volume_usd": 0.0501151018,
            "fees_usd": 2.5e-5,
            "participating_rungs": [
                "B",
                "D"
            ],
            "skipped_rungs": [],
            "depleted_rungs": [],
            "out_of_range_rungs": [
                "A",
                "C",
                "S1",
                "S2",
                "S3"
            ]
        },
        {
            "timestamp": "2026-05-02T03:41:24.000Z",
            "trade_price": 1.002938222211444,
            "price_source": "widest_matching_rung_fill",
            "volume_usd": 195.51700381930002,
            "fees_usd": 0.097539,
            "participating_rungs": [
                "B",
                "D"
            ],
            "skipped_rungs": [],
            "depleted_rungs": [],
            "out_of_range_rungs": [
                "A",
                "C",
                "S1",
                "S2",
                "S3"
            ]
        },
        {
            "timestamp": "2026-05-02T04:49:12.000Z",
            "trade_price": 1.0028918294293112,
            "price_source": "widest_matching_rung_fill",
            "volume_usd": 217.54877575199998,
            "fees_usd": 0.108537,
            "participating_rungs": [
                "A",
                "B",
                "D"
            ],
            "skipped_rungs": [],
            "depleted_rungs": [],
            "out_of_range_rungs": [
                "C",
                "S1",
                "S2",
                "S3"
            ]
        },
        {
            "timestamp": "2026-05-02T05:13:42.000Z",
            "trade_price": 1.0030015007503752,
            "price_source": "widest_matching_rung_fill",
            "volume_usd": 0.0561214892,
            "fees_usd": 2.8e-5,
            "participating_rungs": [
                "A",
                "B",
                "D"
            ],
            "skipped_rungs": [],
            "depleted_rungs": [],
            "out_of_range_rungs": [
                "C",
                "S1",
                "S2",
                "S3"
            ]
        },
        {
            "timestamp": "2026-05-02T05:33:18.000Z",
            "trade_price": 1.0028686744269666,
            "price_source": "widest_matching_rung_fill",
            "volume_usd": 169.7663953933,
            "fees_usd": 0.084702,
            "participating_rungs": [
                "A",
                "B",
                "D"
            ],
            "skipped_rungs": [],
            "depleted_rungs": [],
            "out_of_range_rungs": [
                "C",
                "S1",
                "S2",
                "S3"
            ]
        },
        {
            "timestamp": "2026-05-02T06:06:30.000Z",
            "trade_price": 1.0028514257128562,
            "price_source": "widest_matching_rung_fill",
            "volume_usd": 0.12025741370000001,
            "fees_usd": 6.000000000000001e-5,
            "participating_rungs": [
                "A",
                "B"
            ],
            "skipped_rungs": [
                "D"
            ],
            "depleted_rungs": [],
            "out_of_range_rungs": [
                "C",
                "S1",
                "S2",
                "S3"
            ]
        },
        {
            "timestamp": "2026-05-02T06:19:36.000Z",
            "trade_price": 1.0028470943998105,
            "price_source": "widest_matching_rung_fill",
            "volume_usd": 192.10730760949997,
            "fees_usd": 0.095849,
            "participating_rungs": [
                "A",
                "B",
                "D"
            ],
            "skipped_rungs": [],
            "depleted_rungs": [],
            "out_of_range_rungs": [
                "C",
                "S1",
                "S2",
                "S3"
            ]
        },
        {
            "timestamp": "2026-05-02T07:29:48.001Z",
            "trade_price": 1.0030015007503752,
            "price_source": "widest_matching_rung_fill",
            "volume_usd": 0.0761618937,
            "fees_usd": 3.7999999999999995e-5,
            "participating_rungs": [
                "A",
                "B",
                "D"
            ],
            "skipped_rungs": [],
            "depleted_rungs": [],
            "out_of_range_rungs": [
                "C",
                "S1",
                "S2",
                "S3"
            ]
        },
        {
            "timestamp": "2026-05-02T07:42:24.000Z",
            "trade_price": 1.0028347507086877,
            "price_source": "widest_matching_rung_fill",
            "volume_usd": 0.0721535222,
            "fees_usd": 3.6e-5,
            "participating_rungs": [
                "A",
                "B"
            ],
            "skipped_rungs": [
                "D"
            ],
            "depleted_rungs": [],
            "out_of_range_rungs": [
                "C",
                "S1",
                "S2",
                "S3"
            ]
        }
    ]
}
